rtd_init/__about__.py
rtd_init/__init__.py
rtd_init/rtd_init.py
rtd_init-0.1.7.dist-info/METADATA
rtd_init-0.1.7.dist-info/WHEEL
rtd_init-0.1.7.dist-info/entry_points.txt
rtd_init-0.1.7.dist-info/licenses/LICENSE.txt
rtd_init-0.1.7.dist-info/RECORD
